{"textureWidth":64,"textureHeight":64,"textures":{},"textureSizes":{"head":[64,64]},"elements":[{"name":"EyeFlusteredR","from":[-2.803836584091,-0.156244277954,-0.66755092144],"to":[-2.68983348459,0.101552993059,0.730700731277],"rotationOrigin":[-2.803836584091,-0.156244277954,0.730700731277],"stepParentName":"b_EyeR","rotationX":22.193980830546,"rotationY":1e-12,"rotationZ":-0.0,"group":"eye-flustered","faces":{"north":{"texture":"#head","uv":[8.0,59.0,9.0,60.0],"autoUv":false},"east":{"texture":"#head","uv":[13.0,59.0,16.0,60.0],"autoUv":false},"south":{"texture":"#head","uv":[12.0,59.0,13.0,60.0],"autoUv":false},"west":{"texture":"#head","uv":[9.0,59.0,12.0,60.0],"autoUv":false},"up":{"texture":"#head","uv":[9.0,58.0,12.0,59.0],"autoUv":false,"rotation":90},"down":{"texture":"#head","uv":[12.0,61.0,9.0,60.0],"autoUv":false,"rotation":90}},"children":[]},{"name":"EyebrowL.004","from":[-2.884863615036,0.927604675293,-0.816699624062],"to":[-2.78008724004,1.054069876671,0.022284030914],"rotationOrigin":[-2.884863615036,0.927604675293,-0.816699624062],"stepParentName":"b_EyeL","rotationX":-2.999999656596,"rotationY":1e-12,"rotationZ":0.0,"group":"eye-flustered","faces":{"north":{"texture":"#head","uv":[8.0,60.0,9.0,61.0],"autoUv":false},"east":{"texture":"#head","uv":[13.0,60.0,16.0,61.0],"autoUv":false},"south":{"texture":"#head","uv":[12.0,60.0,13.0,61.0],"autoUv":false},"west":{"texture":"#head","uv":[9.0,60.0,12.0,61.0],"autoUv":false},"up":{"texture":"#head","uv":[9.0,59.0,12.0,60.0],"autoUv":false,"rotation":90},"down":{"texture":"#head","uv":[12.0,62.0,9.0,61.0],"autoUv":false,"rotation":90}},"children":[]},{"name":"EyebrowL.005","from":[-2.884863615036,0.969818115234,-0.074605107307],"to":[-2.780076809227,1.111332952976,0.6867441535],"rotationOrigin":[-2.884863615036,0.969818115234,-0.074605107307],"stepParentName":"b_EyeL","rotationX":6.000002301399,"rotationY":3.7675e-08,"rotationZ":-0.999999031758,"group":"eye-flustered","faces":{"north":{"texture":"#head","uv":[8.0,60.0,9.0,61.0],"autoUv":false},"east":{"texture":"#head","uv":[13.0,60.0,16.0,61.0],"autoUv":false},"south":{"texture":"#head","uv":[12.0,60.0,13.0,61.0],"autoUv":false},"west":{"texture":"#head","uv":[9.0,60.0,12.0,61.0],"autoUv":false},"up":{"texture":"#head","uv":[9.0,59.0,12.0,60.0],"autoUv":false,"rotation":90},"down":{"texture":"#head","uv":[12.0,62.0,9.0,61.0],"autoUv":false,"rotation":90}},"children":[]},{"name":"EyebrowR.004","from":[-2.884863615036,0.927480697632,0.047000169754],"to":[-2.78008724004,1.05394589901,0.88598382473],"rotationOrigin":[-2.884863615036,0.927480697632,0.88598382473],"stepParentName":"b_EyeR","rotationX":2.999999656596,"rotationY":1e-12,"rotationZ":-0.0,"group":"eye-flustered","faces":{"north":{"texture":"#head","uv":[8.0,58.0,9.0,59.0],"autoUv":false},"east":{"texture":"#head","uv":[13.0,58.0,16.0,59.0],"autoUv":false},"south":{"texture":"#head","uv":[12.0,58.0,13.0,59.0],"autoUv":false},"west":{"texture":"#head","uv":[9.0,58.0,12.0,59.0],"autoUv":false},"up":{"texture":"#head","uv":[9.0,57.0,12.0,58.0],"autoUv":false,"rotation":90},"down":{"texture":"#head","uv":[12.0,60.0,9.0,59.0],"autoUv":false,"rotation":90}},"children":[]},{"name":"EyebrowR.005","from":[-2.884863615036,0.969942092896,-0.631856620312],"to":[-2.780076809227,1.111456930637,0.129492640495],"rotationOrigin":[-2.884863615036,0.969942092896,0.129492640495],"stepParentName":"b_EyeR","rotationX":-6.000002301399,"rotationY":-3.7675e-08,"rotationZ":-0.999999031758,"group":"eye-flustered","faces":{"north":{"texture":"#head","uv":[8.0,58.0,9.0,59.0],"autoUv":false},"east":{"texture":"#head","uv":[13.0,58.0,16.0,59.0],"autoUv":false},"south":{"texture":"#head","uv":[12.0,58.0,13.0,59.0],"autoUv":false},"west":{"texture":"#head","uv":[9.0,58.0,12.0,59.0],"autoUv":false},"up":{"texture":"#head","uv":[9.0,57.0,12.0,58.0],"autoUv":false,"rotation":90},"down":{"texture":"#head","uv":[12.0,60.0,9.0,59.0],"autoUv":false,"rotation":90}},"children":[]},{"name":"EyeFlusteredR.001","from":[-2.802797317505,-0.145166397095,-0.41968870163],"to":[-2.688794218004,0.113783746958,0.706010937691],"rotationOrigin":[-2.802797317505,-0.145166397095,0.706010937691],"stepParentName":"b_EyeR","rotationX":-12.922472022854,"rotationY":1e-12,"rotationZ":0.0,"group":"eye-flustered","faces":{"north":{"texture":"#head","uv":[8.0,59.0,9.0,60.0],"autoUv":false},"east":{"texture":"#head","uv":[13.0,59.0,16.0,60.0],"autoUv":false},"south":{"texture":"#head","uv":[12.0,59.0,13.0,60.0],"autoUv":false},"west":{"texture":"#head","uv":[9.0,59.0,12.0,60.0],"autoUv":false},"up":{"texture":"#head","uv":[9.0,58.0,12.0,59.0],"autoUv":false,"rotation":90},"down":{"texture":"#head","uv":[12.0,61.0,9.0,60.0],"autoUv":false,"rotation":90}},"children":[]},{"name":"EyeFlusteredL","from":[-2.803836584091,-0.156244277954,-0.730700731277],"to":[-2.68983348459,0.101552993059,0.66755092144],"rotationOrigin":[-2.803836584091,-0.156244277954,-0.730700731277],"stepParentName":"b_EyeL","rotationX":-22.193980830546,"rotationY":1e-12,"rotationZ":0.0,"group":"eye-flustered","faces":{"north":{"texture":"#head","uv":[13.0,59.0,12.0,60.0],"autoUv":false},"east":{"texture":"#head","uv":[16.0,59.0,13.0,60.0],"autoUv":false},"south":{"texture":"#head","uv":[9.0,59.0,8.0,60.0],"autoUv":false},"west":{"texture":"#head","uv":[12.0,59.0,9.0,60.0],"autoUv":false},"up":{"texture":"#head","uv":[12.0,58.0,9.0,59.0],"autoUv":false,"rotation":90},"down":{"texture":"#head","uv":[9.0,61.0,12.0,60.0],"autoUv":false,"rotation":90}},"children":[]},{"name":"EyeFlusteredL.001","from":[-2.802797317505,-0.145166397095,-0.706010937691],"to":[-2.688794218004,0.113783746958,0.41968870163],"rotationOrigin":[-2.802797317505,-0.145166397095,-0.706010937691],"stepParentName":"b_EyeL","rotationX":12.922472022854,"rotationY":1e-12,"rotationZ":-0.0,"group":"eye-flustered","faces":{"north":{"texture":"#head","uv":[13.0,59.0,12.0,60.0],"autoUv":false},"east":{"texture":"#head","uv":[16.0,59.0,13.0,60.0],"autoUv":false},"south":{"texture":"#head","uv":[9.0,59.0,8.0,60.0],"autoUv":false},"west":{"texture":"#head","uv":[12.0,59.0,9.0,60.0],"autoUv":false},"up":{"texture":"#head","uv":[12.0,58.0,9.0,59.0],"autoUv":false,"rotation":90},"down":{"texture":"#head","uv":[9.0,61.0,12.0,60.0],"autoUv":false,"rotation":90}},"children":[]}],"groups":[]}