{"textureWidth": 96, "textureHeight": 96, "textures": {"hair": "kemono:entity/horse/hair/hair"}, "textureSizes": {"hair": [96, 96]}, "elements": [{"name": "hair-uncovered", "from": [-2.76149511, 4.37295055, -3.32292247], "to": [-1.60149515, 5.53295052, -2.1629225], "rotationOrigin": [-2.76149511, 4.37295055, -3.32292247], "stepParentName": "b_Head", "rotationX": -0.0, "rotationY": 0.0, "rotationZ": -90.00000933, "group": "hair-carepackage", "faces": {"north": {"texture": "#disable", "uv": [0, 0, 4, 4], "autoUv": false, "enabled": false}, "east": {"texture": "#disable", "uv": [0, 0, 4, 4], "autoUv": false, "enabled": false}, "south": {"texture": "#disable", "uv": [0, 0, 4, 4], "autoUv": false, "enabled": false}, "west": {"texture": "#disable", "uv": [0, 0, 4, 4], "autoUv": false, "enabled": false}, "up": {"texture": "#disable", "uv": [0, 0, 4, 4], "autoUv": false, "enabled": false}, "down": {"texture": "#disable", "uv": [0, 0, 4, 4], "autoUv": false, "enabled": false}}, "children": [{"name": "Hairstrand.171", "from": [3.3403857, 5.2347613, 3.81289655], "to": [5.01021741, 10.25699806, 6.13091964], "rotationOrigin": [4.17530155, 10.25699806, 4.97190809], "rotationX": 12.49070503, "rotationY": -19.6761699, "rotationZ": -88.96707983, "group": "hair-carepackage", "faces": {"north": {"texture": "#hair", "uv": [41.00000095, 0.0, 42.99999905, 7.99999809], "autoUv": false}, "east": {"texture": "#hair", "uv": [41.00000095, 1.00000191, 45.0, 9.0], "autoUv": false}, "south": {"texture": "#hair", "uv": [41.00000095, 1.00000191, 42.99999905, 9.0], "autoUv": false}, "west": {"texture": "#hair", "uv": [76.99999809, 22.99999809, 81.0, 31.00000191], "autoUv": false}, "up": {"texture": "#hair", "uv": [42.0, 3.0, 45.99999905, 4.99999809], "autoUv": false, "rotation": 270}, "down": {"texture": "#hair", "uv": [41.00000095, 6.0, 45.0, 4.00000191], "autoUv": false, "rotation": 270}}, "children": []}, {"name": "Hairstrand.177", "from": [4.66291622, 5.10591718, 2.25035133], "to": [6.07217185, 10.03389174, 3.87147055], "rotationOrigin": [5.36754417, 10.03389359, 3.06091094], "rotationX": 63.13078963, "rotationY": -9.87474002, "rotationZ": -43.12973836, "faces": {"north": {"texture": "#hair", "uv": [54.0, 0.0, 58.00000191, 10.99999809], "autoUv": false}, "east": {"texture": "#hair", "uv": [36.99999905, 0.0, 39.99999905, 10.99999809], "autoUv": false}, "south": {"texture": "#disable", "uv": [0, 0, 4, 4], "autoUv": false, "enabled": false}, "west": {"texture": "#hair", "uv": [49.99999809, 0.0, 52.99999809, 10.99999809], "autoUv": false}, "up": {"texture": "#hair", "uv": [39.0, 1.99999809, 42.99999905, 4.99999809], "autoUv": false}, "down": {"texture": "#disable", "uv": [0, 0, 4, 4], "autoUv": false, "enabled": false}}, "children": []}, {"name": "Hairstrand.189", "from": [5.94441891, 3.07148194, 2.47727238], "to": [9.01652527, 9.04848671, 4.34241165], "rotationOrigin": [7.48047209, 9.04848671, 3.40984201], "rotationX": 78.82559446, "rotationY": -44.116226, "rotationZ": -85.18079861, "group": "hair-carepackage", "faces": {"north": {"texture": "#hair", "uv": [36.0, 3.0, 39.99999905, 12.0], "autoUv": false}, "east": {"texture": "#hair", "uv": [85.00000191, 31.99999809, 82.00000191, 40.99999809], "autoUv": false}, "south": {"texture": "#hair", "uv": [33.99999905, 4.00000191, 39.0, 13.00000191], "autoUv": false}, "west": {"texture": "#hair", "uv": [45.99999905, 3.0, 42.99999905, 12.0], "autoUv": false}, "up": {"texture": "#hair", "uv": [35.00000095, 4.00000191, 39.0, 6.0], "autoUv": false}, "down": {"texture": "#disable", "uv": [0, 0, 4, 4], "autoUv": false, "enabled": false}}, "children": []}, {"name": "Hairstrand.193", "from": [0.23614453, 7.11123771, 0.09149819], "to": [1.22493507, 10.56515312, 2.45113534], "rotationOrigin": [0.7305398, 10.56515312, 1.27131677], "rotationX": -24.63225762, "rotationY": -37.22227018, "rotationZ": -113.87169807, "group": "hair-carepackage", "faces": {"north": {"texture": "#hair", "uv": [42.99999905, 6.0, 45.0, 10.99999809], "autoUv": false}, "east": {"texture": "#disable", "uv": [0, 0, 4, 4], "autoUv": false, "enabled": false}, "south": {"texture": "#hair", "uv": [41.00000095, 6.0, 42.99999905, 10.99999809], "autoUv": false}, "west": {"texture": "#hair", "uv": [41.00000095, 6.0, 45.0, 10.99999809], "autoUv": false}, "up": {"texture": "#hair", "uv": [41.00000095, 3.0, 45.0, 4.99999809], "autoUv": false, "rotation": 270}, "down": {"texture": "#hair", "uv": [44.00000095, 16.99999809, 39.99999905, 15.0], "autoUv": false, "rotation": 90}}, "children": []}, {"name": "Hairstrand.196", "from": [4.06848864, 5.7826039, 3.45022177], "to": [7.42297347, 11.01812166, 5.16482569], "rotationOrigin": [5.74573135, 11.01812363, 4.30752373], "rotationX": 63.68527122, "rotationY": -14.7880255, "rotationZ": -60.5007365, "group": "hair-carepackage", "faces": {"north": {"texture": "#hair", "uv": [38.00000095, 0.0, 42.99999905, 7.99999809], "autoUv": false}, "east": {"texture": "#hair", "uv": [30.99999905, 0.0, 33.99999905, 7.99999809], "autoUv": false}, "south": {"texture": "#hair", "uv": [32.00000095, 1.00000191, 36.99999905, 9.0], "autoUv": false}, "west": {"texture": "#hair", "uv": [49.00000191, 1.00000191, 52.00000191, 9.0], "autoUv": false}, "up": {"texture": "#hair", "uv": [36.0, 1.99999809, 41.00000095, 4.00000191], "autoUv": false}, "down": {"texture": "#hair", "uv": [36.99999905, 6.0, 42.0, 4.00000191], "autoUv": false, "rotation": 180}}, "children": []}, {"name": "Hairstrand.197", "from": [0.43398719, 7.51685661, 1.35080883], "to": [3.5435295, 10.97644867, 2.42856291], "rotationOrigin": [1.98875856, 10.97644997, 1.88968587], "rotationX": 66.11185301, "rotationY": -13.9597037, "rotationZ": -50.30611226, "group": "hair-carepackage", "faces": {"north": {"texture": "#hair", "uv": [39.99999905, 4.99999809, 45.0, 10.99999809], "autoUv": false}, "east": {"texture": "#hair", "uv": [30.99999905, 1.00000191, 33.0, 7.00000191], "autoUv": false}, "south": {"texture": "#hair", "uv": [41.00000095, 6.0, 45.99999905, 12.0], "autoUv": false}, "west": {"texture": "#hair", "uv": [41.00000095, 4.99999809, 42.99999905, 10.99999809], "autoUv": false}, "up": {"texture": "#hair", "uv": [36.0, 1.99999809, 41.00000095, 4.00000191], "autoUv": false}, "down": {"texture": "#hair", "uv": [33.99999905, 16.00000191, 39.0, 13.99999809], "autoUv": false, "rotation": 180}}, "children": []}, {"name": "Hairstrand.200", "from": [4.05271193, 5.31486006, 2.1990596], "to": [5.29311804, 10.65018845, 4.70238626], "rotationOrigin": [4.67291498, 10.65018845, 3.45072293], "rotationX": -27.45691992, "rotationY": -31.03325478, "rotationZ": -123.48331785, "group": "hair-carepackage", "faces": {"north": {"texture": "#hair", "uv": [44.00000095, 4.00000191, 45.99999905, 12.0], "autoUv": false}, "east": {"texture": "#disable", "uv": [0, 0, 4, 4], "autoUv": false, "enabled": false}, "south": {"texture": "#hair", "uv": [41.00000095, 3.0, 42.99999905, 10.99999809], "autoUv": false}, "west": {"texture": "#hair", "uv": [41.00000095, 3.0, 45.0, 10.99999809], "autoUv": false}, "up": {"texture": "#hair", "uv": [42.0, 3.0, 44.00000095, 7.00000191], "autoUv": false}, "down": {"texture": "#disable", "uv": [0, 0, 4, 4], "autoUv": false, "enabled": false}}, "children": []}]}, {"name": "bangs", "from": [-2.76149511, 4.37295055, -2.16292238], "to": [-1.60149515, 5.53295052, -1.00292242], "rotationOrigin": [-2.76149511, 4.37295055, -2.16292238], "stepParentName": "b_Head", "rotationX": -0.0, "rotationY": 0.0, "rotationZ": -90.00000933, "group": "hair-carepackage", "faces": {"north": {"texture": "#disable", "uv": [0, 0, 4, 4], "autoUv": false, "enabled": false}, "east": {"texture": "#disable", "uv": [0, 0, 4, 4], "autoUv": false, "enabled": false}, "south": {"texture": "#disable", "uv": [0, 0, 4, 4], "autoUv": false, "enabled": false}, "west": {"texture": "#disable", "uv": [0, 0, 4, 4], "autoUv": false, "enabled": false}, "up": {"texture": "#disable", "uv": [0, 0, 4, 4], "autoUv": false, "enabled": false}, "down": {"texture": "#disable", "uv": [0, 0, 4, 4], "autoUv": false, "enabled": false}}, "children": [{"name": "Hairstrand.173", "from": [-0.38229716, 5.82126561, 1.29533243], "to": [1.28753436, 10.84350204, 3.74486875], "rotationOrigin": [0.4526186, 10.84350204, 2.52010059], "rotationX": 12.52827875, "rotationY": -32.74342828, "rotationZ": -30.64666265, "group": "hair-carepackage", "faces": {"north": {"texture": "#hair", "uv": [41.00000095, 0.0, 42.99999905, 7.99999809], "autoUv": false}, "east": {"texture": "#hair", "uv": [41.00000095, 1.00000191, 45.0, 9.0], "autoUv": false}, "south": {"texture": "#hair", "uv": [41.00000095, 1.00000191, 42.99999905, 9.0], "autoUv": false}, "west": {"texture": "#hair", "uv": [76.99999809, 22.99999809, 81.0, 31.00000191], "autoUv": false}, "up": {"texture": "#hair", "uv": [42.0, 3.0, 45.99999905, 4.99999809], "autoUv": false, "rotation": 270}, "down": {"texture": "#hair", "uv": [41.00000095, 6.0, 45.0, 4.00000191], "autoUv": false, "rotation": 270}}, "children": []}, {"name": "Hairstrand.186", "from": [1.18479587, 3.93192899, -0.22073184], "to": [2.47090005, 9.80921745, 2.77814398], "rotationOrigin": [1.82784796, 9.80921745, 1.27870607], "rotationX": -15.144003, "rotationY": -44.071338, "rotationZ": -81.29204407, "group": "hair-carepackage", "faces": {"north": {"texture": "#hair", "uv": [44.00000095, 4.00000191, 45.99999905, 12.0], "autoUv": false}, "east": {"texture": "#disable", "uv": [0, 0, 4, 4], "autoUv": false, "enabled": false}, "south": {"texture": "#hair", "uv": [41.00000095, 3.0, 42.99999905, 10.99999809], "autoUv": false}, "west": {"texture": "#hair", "uv": [41.00000095, 3.0, 45.0, 10.99999809], "autoUv": false}, "up": {"texture": "#hair", "uv": [42.0, 1.99999809, 44.00000095, 7.00000191], "autoUv": false}, "down": {"texture": "#disable", "uv": [0, 0, 4, 4], "autoUv": false, "enabled": false}}, "children": []}, {"name": "Hairstrand.194", "from": [0.0072481, 5.74596604, 3.2892329], "to": [1.37391455, 9.99312401, 5.2685445], "rotationOrigin": [0.69058132, 9.99312401, 4.2788887], "rotationX": 20.89211262, "rotationY": 5.59468991, "rotationZ": -36.12135297, "group": "hair-carepackage", "faces": {"north": {"texture": "#hair", "uv": [42.99999905, 4.99999809, 41.00000095, 10.99999809], "autoUv": false}, "east": {"texture": "#hair", "uv": [44.00000095, 6.0, 41.00000095, 12.0], "autoUv": false}, "south": {"texture": "#hair", "uv": [44.00000095, 6.0, 42.0, 12.0], "autoUv": false}, "west": {"texture": "#hair", "uv": [82.00000191, 34.99999809, 85.00000191, 40.99999809], "autoUv": false}, "up": {"texture": "#hair", "uv": [45.0, 3.0, 42.0, 4.99999809], "autoUv": false, "rotation": 270}, "down": {"texture": "#disable", "uv": [0, 0, 4, 4], "autoUv": false, "enabled": false}}, "children": []}, {"name": "Hairstrand.195", "from": [-2.30858902, 5.00567931, -0.39360523], "to": [-0.94322868, 7.42907143, 1.48388958], "rotationOrigin": [-1.62590885, 7.42907143, 0.54514217], "rotationX": 7.04845384, "rotationY": -29.0033772, "rotationZ": -31.36033205, "group": "hair-carepackage", "faces": {"north": {"texture": "#hair", "uv": [41.00000095, 7.00000191, 42.99999905, 10.99999809], "autoUv": false}, "east": {"texture": "#hair", "uv": [39.99999905, 7.99999809, 42.99999905, 12.0], "autoUv": false}, "south": {"texture": "#hair", "uv": [41.00000095, 7.00000191, 42.99999905, 10.99999809], "autoUv": false}, "west": {"texture": "#hair", "uv": [82.99999809, 37.99999809, 79.99999809, 42.0], "autoUv": false}, "up": {"texture": "#hair", "uv": [41.00000095, 3.0, 44.00000095, 4.99999809], "autoUv": false, "rotation": 270}, "down": {"texture": "#disable", "uv": [0, 0, 4, 4], "autoUv": false, "enabled": false}}, "children": []}]}, {"name": "ponytailhigh", "from": [-2.76149511, 4.37295055, -1.00292242], "to": [-1.60149515, 5.53295052, 0.15707755], "rotationOrigin": [-2.76149511, 4.37295055, -1.00292242], "stepParentName": "b_Head", "rotationX": -0.0, "rotationY": 0.0, "rotationZ": -90.00000933, "group": "hair-carepackage", "faces": {"north": {"texture": "#disable", "uv": [0, 0, 4, 4], "autoUv": false, "enabled": false}, "east": {"texture": "#disable", "uv": [0, 0, 4, 4], "autoUv": false, "enabled": false}, "south": {"texture": "#disable", "uv": [0, 0, 4, 4], "autoUv": false, "enabled": false}, "west": {"texture": "#disable", "uv": [0, 0, 4, 4], "autoUv": false, "enabled": false}, "up": {"texture": "#disable", "uv": [0, 0, 4, 4], "autoUv": false, "enabled": false}, "down": {"texture": "#disable", "uv": [0, 0, 4, 4], "autoUv": false, "enabled": false}}, "children": [{"name": "Hairstrand.176", "from": [7.11529773, 4.57202196, -0.65913475], "to": [8.19519383, 9.85568428, 2.34233201], "rotationOrigin": [7.65524578, 9.85568428, 0.84159863], "rotationX": -13.46738537, "rotationY": -10.39425957, "rotationZ": -17.00474632, "group": "hair-carepackage", "faces": {"north": {"texture": "#hair", "uv": [32.00000095, 4.00000191, 33.99999905, 12.0], "autoUv": false}, "east": {"texture": "#hair", "uv": [73.00000191, 31.99999809, 76.99999809, 40.00000191], "autoUv": false}, "south": {"texture": "#hair", "uv": [38.00000095, 4.00000191, 39.99999905, 12.0], "autoUv": false}, "west": {"texture": "#hair", "uv": [41.00000095, 4.00000191, 45.99999905, 12.0], "autoUv": false}, "up": {"texture": "#hair", "uv": [39.0, 4.00000191, 42.99999905, 6.0], "autoUv": false, "rotation": 90}, "down": {"texture": "#disable", "uv": [0, 0, 4, 4], "autoUv": false, "enabled": false}}, "children": []}, {"name": "Hairstrand.181", "from": [4.67059338, 4.8479228, -0.0140354], "to": [7.3777808, 9.01797485, 1.30562204], "rotationOrigin": [6.02418709, 9.01797485, 0.64579332], "rotationX": -110.66811395, "rotationY": 37.65629797, "rotationZ": 120.31756615, "group": "hair-carepackage", "faces": {"north": {"texture": "#hair", "uv": [41.00000095, 7.00000191, 45.0, 12.0], "autoUv": false}, "east": {"texture": "#hair", "uv": [35.00000095, 6.0, 36.99999905, 10.99999809], "autoUv": false}, "south": {"texture": "#hair", "uv": [41.00000095, 6.0, 45.0, 10.99999809], "autoUv": false}, "west": {"texture": "#hair", "uv": [36.99999905, 6.0, 39.0, 10.99999809], "autoUv": false}, "up": {"texture": "#hair", "uv": [36.99999905, 1.99999809, 41.00000095, 4.00000191], "autoUv": false}, "down": {"texture": "#disable", "uv": [0, 0, 4, 4], "autoUv": false, "enabled": false}}, "children": []}, {"name": "Hairstrand.188", "from": [3.18619227, -1.68602467, -0.2703588], "to": [6.29678178, 3.47143364, 1.88934779], "rotationOrigin": [4.74148703, 3.47143364, 0.8094945], "rotationX": -103.06017797, "rotationY": -42.4111205, "rotationZ": 83.93491746, "group": "hair-carepackage", "faces": {"north": {"texture": "#hair", "uv": [41.00000095, 4.99999809, 45.0, 10.99999809], "autoUv": false}, "east": {"texture": "#hair", "uv": [30.99999905, 4.99999809, 33.99999905, 10.99999809], "autoUv": false}, "south": {"texture": "#hair", "uv": [41.00000095, 4.99999809, 45.0, 10.99999809], "autoUv": false}, "west": {"texture": "#hair", "uv": [38.00000095, 6.0, 35.00000095, 12.0], "autoUv": false}, "up": {"texture": "#hair", "uv": [36.0, 4.99999809, 39.99999905, 7.00000191], "autoUv": false}, "down": {"texture": "#disable", "uv": [0, 0, 4, 4], "autoUv": false, "enabled": false}}, "children": []}, {"name": "Hairstrand.192", "from": [4.46924627, -0.25859118, 0.23132223], "to": [7.35262263, 3.2632637, 1.90423375], "rotationOrigin": [5.91093445, 3.2632637, 1.06777799], "rotationX": -92.31988992, "rotationY": -37.17483794, "rotationZ": 88.64018014, "group": "hair-carepackage", "faces": {"north": {"texture": "#hair", "uv": [42.0, 4.99999809, 47.00000095, 10.99999809], "autoUv": false}, "east": {"texture": "#hair", "uv": [36.99999905, 6.0, 39.99999905, 12.0], "autoUv": false}, "south": {"texture": "#hair", "uv": [36.99999905, 4.99999809, 42.0, 10.99999809], "autoUv": false}, "west": {"texture": "#hair", "uv": [39.99999905, 4.00000191, 42.99999905, 10.00000191], "autoUv": false}, "up": {"texture": "#hair", "uv": [36.0, 0.0, 41.00000095, 3.0], "autoUv": false}, "down": {"texture": "#disable", "uv": [0, 0, 4, 4], "autoUv": false, "enabled": false}}, "children": []}, {"name": "Hairstrand.198", "from": [5.40598643, 3.35549521, -0.2085939], "to": [7.89831674, 8.33138084, 1.4400664], "rotationOrigin": [6.65215158, 8.33138084, 0.61573625], "rotationX": -33.08586664, "rotationY": 99.75800007, "rotationZ": 27.08256237, "group": "hair-carepackage", "faces": {"north": {"texture": "#hair", "uv": [79.00000191, 30.0, 82.00000191, 37.00000191], "autoUv": false}, "east": {"texture": "#hair", "uv": [73.99999809, 30.0, 76.00000191, 37.00000191], "autoUv": false}, "south": {"texture": "#hair", "uv": [79.99999809, 31.00000191, 82.99999809, 37.99999809], "autoUv": false}, "west": {"texture": "#hair", "uv": [73.00000191, 73.99999952, 75.0, 81.0], "autoUv": false}, "up": {"texture": "#hair", "uv": [67.99999809, 73.00000048, 70.99999809, 75.0], "autoUv": false}, "down": {"texture": "#disable", "uv": [0, 0, 4, 4], "autoUv": false, "enabled": false}}, "children": []}, {"name": "Hairstrand.199", "from": [5.02038848, 4.64798212, 0.18367875], "to": [7.65261281, 9.82141304, 1.84920204], "rotationOrigin": [6.33650064, 9.82141304, 1.01644039], "rotationX": -61.80705799, "rotationY": 51.96307858, "rotationZ": 51.5068117, "group": "hair-carepackage", "faces": {"north": {"texture": "#hair", "uv": [41.00000095, 4.99999809, 45.0, 12.0], "autoUv": false}, "east": {"texture": "#hair", "uv": [35.00000095, 4.00000191, 38.00000095, 10.99999809], "autoUv": false}, "south": {"texture": "#hair", "uv": [36.99999905, 4.00000191, 41.00000095, 10.99999809], "autoUv": false}, "west": {"texture": "#hair", "uv": [36.99999905, 4.99999809, 39.99999905, 12.0], "autoUv": false}, "up": {"texture": "#hair", "uv": [36.99999905, 1.99999809, 41.00000095, 4.99999809], "autoUv": false}, "down": {"texture": "#disable", "uv": [0, 0, 4, 4], "autoUv": false, "enabled": false}}, "children": []}, {"name": "Hairstrand.201", "from": [3.64969914, 5.50869846, -0.22926307], "to": [6.53964717, 9.52423477, 1.59933364], "rotationOrigin": [5.09467316, 9.52423477, 0.68503529], "rotationX": -89.47109315, "rotationY": 21.40558063, "rotationZ": 85.81267307, "group": "hair-carepackage", "faces": {"north": {"texture": "#hair", "uv": [41.00000095, 4.99999809, 45.0, 12.0], "autoUv": false}, "east": {"texture": "#hair", "uv": [24.0, 4.99999809, 27.0, 12.0], "autoUv": false}, "south": {"texture": "#hair", "uv": [41.00000095, 4.00000191, 45.0, 10.99999809], "autoUv": false}, "west": {"texture": "#hair", "uv": [36.99999905, 4.99999809, 39.99999905, 12.0], "autoUv": false}, "up": {"texture": "#hair", "uv": [36.99999905, 1.99999809, 41.00000095, 4.99999809], "autoUv": false}, "down": {"texture": "#disable", "uv": [0, 0, 4, 4], "autoUv": false, "enabled": false}}, "children": []}]}, {"name": "sidehigh", "from": [-2.76149511, 4.37295055, 0.15707755], "to": [-1.60149515, 5.53295052, 1.31707752], "rotationOrigin": [-2.76149511, 4.37295055, 0.15707755], "stepParentName": "b_Head", "rotationX": -0.0, "rotationY": 0.0, "rotationZ": -90.00000933, "group": "hair-carepackage", "faces": {"north": {"texture": "#disable", "uv": [0, 0, 4, 4], "autoUv": false, "enabled": false}, "east": {"texture": "#disable", "uv": [0, 0, 4, 4], "autoUv": false, "enabled": false}, "south": {"texture": "#disable", "uv": [0, 0, 4, 4], "autoUv": false, "enabled": false}, "west": {"texture": "#disable", "uv": [0, 0, 4, 4], "autoUv": false, "enabled": false}, "up": {"texture": "#disable", "uv": [0, 0, 4, 4], "autoUv": false, "enabled": false}, "down": {"texture": "#disable", "uv": [0, 0, 4, 4], "autoUv": false, "enabled": false}}, "children": [{"name": "Hairstrand.182", "from": [2.86581453, 4.50255785, -0.79040681], "to": [6.22029976, 10.06441099, 0.52207853], "rotationOrigin": [4.54305744, 10.06441307, -0.13416414], "rotationX": 62.26690047, "rotationY": -3.93997285, "rotationZ": -59.49331092, "group": "hair-carepackage", "faces": {"north": {"texture": "#hair", "uv": [38.00000095, 0.0, 42.99999905, 7.99999809], "autoUv": false}, "east": {"texture": "#hair", "uv": [30.99999905, 0.0, 33.0, 7.99999809], "autoUv": false}, "south": {"texture": "#hair", "uv": [32.00000095, 1.00000191, 36.99999905, 9.0], "autoUv": false}, "west": {"texture": "#hair", "uv": [49.99999809, 1.00000191, 52.00000191, 9.0], "autoUv": false}, "up": {"texture": "#hair", "uv": [36.0, 1.99999809, 41.00000095, 4.00000191], "autoUv": false}, "down": {"texture": "#hair", "uv": [36.99999905, 6.0, 42.0, 4.00000191], "autoUv": false, "rotation": 180}}, "children": []}, {"name": "Hairstrand.184", "from": [4.88737961, 4.4055093, -1.43710708], "to": [6.12778572, 9.7408371, 1.21462969], "rotationOrigin": [5.50758266, 9.7408371, -0.1112387], "rotationX": -20.73167148, "rotationY": -35.69631372, "rotationZ": -100.90961095, "group": "hair-carepackage", "faces": {"north": {"texture": "#hair", "uv": [44.00000095, 4.00000191, 45.99999905, 12.0], "autoUv": false}, "east": {"texture": "#disable", "uv": [0, 0, 4, 4], "autoUv": false, "enabled": false}, "south": {"texture": "#hair", "uv": [41.00000095, 3.0, 42.99999905, 10.99999809], "autoUv": false}, "west": {"texture": "#hair", "uv": [41.00000095, 3.0, 45.0, 10.99999809], "autoUv": false}, "up": {"texture": "#hair", "uv": [42.0, 3.0, 44.00000095, 7.00000191], "autoUv": false}, "down": {"texture": "#disable", "uv": [0, 0, 4, 4], "autoUv": false, "enabled": false}}, "children": []}, {"name": "Hairstrand.191", "from": [4.9055521, 4.41840595, -0.04735112], "to": [7.54617425, 10.62696033, 1.84923649], "rotationOrigin": [6.22586346, 10.62696266, 0.90094268], "rotationX": 113.05253299, "rotationY": 6.49451654, "rotationZ": -99.51923032, "group": "hair-carepackage", "faces": {"north": {"texture": "#hair", "uv": [75.0, 28.00000191, 79.00000191, 36.0], "autoUv": false}, "east": {"texture": "#hair", "uv": [81.0, 28.00000191, 84.0, 36.0], "autoUv": false}, "south": {"texture": "#hair", "uv": [79.99999809, 28.00000191, 84.0, 36.0], "autoUv": false}, "west": {"texture": "#hair", "uv": [76.99999809, 28.00000191, 79.99999809, 36.0], "autoUv": false}, "up": {"texture": "#hair", "uv": [79.00000191, 28.99999809, 82.99999809, 31.99999809], "autoUv": false}, "down": {"texture": "#hair", "uv": [82.00000191, 34.00000191, 78.0, 30.0], "autoUv": false, "rotation": 180}}, "children": []}]}], "groups": []}